Metadata-Version: 1.0
Name: wzry-spider
Version: 1.0.1
Summary: A spider to download wzry-hero image
Home-page: https://github.com/y-super-y/
Author: super_chao
Author-email: 3160889328@qq.com
License: MIT
Keywords: wzry,image,spider,download
Platform: UNKNOWN
